asyncpygame/__init__.py
asyncpygame/_priority_executor.py
asyncpygame/_runner.py
asyncpygame/_sdlevent.py
asyncpygame/_utils.py
asyncpygame/constants.py
asyncpygame/scene_switcher.py
asyncpygame-0.1.3.dist-info/LICENSE
asyncpygame-0.1.3.dist-info/METADATA
asyncpygame-0.1.3.dist-info/WHEEL
asyncpygame-0.1.3.dist-info/RECORD
