Metadata-Version: 2.1
Name: asyncpygame
Version: 0.1.3
Summary: Async/await-based framework for PyGame
Home-page: https://github.com/asyncgui/asyncpygame
License: MIT
Keywords: async,pygame
Author: Nattōsai Mitō
Author-email: flow4re2c@gmail.com
Requires-Python: >=3.10,<4.0
Classifier: Development Status :: 2 - Pre-Alpha
Classifier: Intended Audience :: Developers
Classifier: License :: OSI Approved :: MIT License
Classifier: Operating System :: OS Independent
Classifier: Programming Language :: Python
Classifier: Programming Language :: Python :: 3
Classifier: Programming Language :: Python :: 3.10
Classifier: Programming Language :: Python :: 3.11
Classifier: Programming Language :: Python :: 3.12
Classifier: Topic :: Software Development :: Libraries
Requires-Dist: asyncgui (>=0.7,<0.8)
Requires-Dist: asyncgui-ext-clock (>=0.5,<0.6)
Requires-Dist: pygame-ce (>=2.5,<2.6)
Project-URL: Repository, https://github.com/asyncgui/asyncpygame
